{
  "www": {
    "port": "PORT"
  },
  "sentry": {
    "dsn": "SENTRY_DSN",
    "env": "SENTRY_ENV"
  },
  "papertrail": {
    "host": "PAPERTRAIL_HOST",
    "port": "PAPERTRAIL_PORT",
    "program": "PAPERTRAIL_PROGRAM"
  },
  "blockchain": {
    "websocket": {
      "port": "BLOCKCHAIN_WEBSOCKET_PORT",
      "peers": "BLOCKCHAIN_PEERS"
    },
    "difficulty": "BLOCKCHAIN_INITIAL_DIFFICULTY",
    "miningRate": "BLOCKCHAIN_MINING_RATE",
    "walletInitialBalance": "BLOCKCHAIN_WALLET_INITIAL_BALANCE",
    "miningReward": "BLOCKCHAIN_MINING_REWARD"
  }
}
